openstack_cli/__init__.py
openstack_cli/cli.py
openstack_cli/commands/__init__.py
openstack_cli/commands/buy.py
openstack_cli/commands/config.py
openstack_cli/commands/gift.py
openstack_cli/commands/info.py
openstack_cli/commands/init.py
openstack_cli/commands/login.py
openstack_cli/commands/logout.py
openstack_cli/commands/register.py
openstack_cli/config/config.json
openstack_cli/utils/__init__.py
openstack_cli/utils/authentication.py
openstack_cli/utils/config_tools.py
openstack_cli/utils/decorators.py
openstack_cli/utils/rename_project.py
openstack_cli/utils/themes.py
tests/__init__.py
tests/test_gifts.py
tests/test_init.py
tests/test_login.py
openstack_cli-0.0.7.dist-info/AUTHORS
openstack_cli-0.0.7.dist-info/LICENCE
openstack_cli-0.0.7.dist-info/METADATA
openstack_cli-0.0.7.dist-info/WHEEL
openstack_cli-0.0.7.dist-info/entry_points.txt
openstack_cli-0.0.7.dist-info/top_level.txt
openstack_cli-0.0.7.dist-info/RECORD
