Metadata-Version: 2.1
Name: openstack-cli
Version: 0.0.7
Summary: short package description
Author: abdelrhman yasser
Author-email: abdo.afage2@gmail.com
Classifier: Development Status :: 2 - Pre-Alpha
Classifier: Intended Audience :: Developers
Classifier: Programming Language :: Python :: 3
Classifier: License :: OSI Approved :: MIT License
Classifier: Operating System :: OS Independent
Requires-Python: >=3.7
License-File: LICENCE
License-File: AUTHORS
Requires-Dist: setuptools (==45.2.0)
Requires-Dist: click (==7.1.2)
Requires-Dist: tabulate (==0.9.0)
Requires-Dist: spinners (==0.0.24)
Requires-Dist: termcolor (==2.1.1)
Requires-Dist: halo (==0.0.31)
Requires-Dist: inquirer (==3.1.2)
Requires-Dist: requests (==2.28.1)
Requires-Dist: blessed (==1.19.1)
